odoo/addons/server_environment_ir_config_parameter/README.rst
odoo/addons/server_environment_ir_config_parameter/__init__.py
odoo/addons/server_environment_ir_config_parameter/__manifest__.py
odoo/addons/server_environment_ir_config_parameter/i18n/de.po
odoo/addons/server_environment_ir_config_parameter/i18n/es.po
odoo/addons/server_environment_ir_config_parameter/i18n/it.po
odoo/addons/server_environment_ir_config_parameter/i18n/nl_NL.po
odoo/addons/server_environment_ir_config_parameter/i18n/ro.po
odoo/addons/server_environment_ir_config_parameter/i18n/server_environment_ir_config_parameter.pot
odoo/addons/server_environment_ir_config_parameter/i18n/sv.po
odoo/addons/server_environment_ir_config_parameter/models/__init__.py
odoo/addons/server_environment_ir_config_parameter/models/ir_config_parameter.py
odoo/addons/server_environment_ir_config_parameter/readme/CONFIGURE.md
odoo/addons/server_environment_ir_config_parameter/readme/CONTRIBUTORS.md
odoo/addons/server_environment_ir_config_parameter/readme/CREDITS.md
odoo/addons/server_environment_ir_config_parameter/readme/DESCRIPTION.md
odoo/addons/server_environment_ir_config_parameter/readme/ROADMAP.md
odoo/addons/server_environment_ir_config_parameter/readme/USAGE.md
odoo/addons/server_environment_ir_config_parameter/static/description/icon.png
odoo/addons/server_environment_ir_config_parameter/static/description/index.html
odoo/addons/server_environment_ir_config_parameter/tests/__init__.py
odoo/addons/server_environment_ir_config_parameter/tests/config_param_test.xml
odoo/addons/server_environment_ir_config_parameter/tests/test_server_environment_ircp.py
odoo/addons/server_environment_ir_config_parameter/views/view_ir_config_parameter.xml
odoo_addon_server_environment_ir_config_parameter-18.0.1.0.0.6.dist-info/METADATA
odoo_addon_server_environment_ir_config_parameter-18.0.1.0.0.6.dist-info/WHEEL
odoo_addon_server_environment_ir_config_parameter-18.0.1.0.0.6.dist-info/top_level.txt
odoo_addon_server_environment_ir_config_parameter-18.0.1.0.0.6.dist-info/RECORD
